grafci/__init__.py
grafci/pytest_helpers.py
grafci/repo_observer.py
grafci/result_collector.py
grafci-0.1.0.dist-info/entry_points.txt
grafci-0.1.0.dist-info/WHEEL
grafci-0.1.0.dist-info/METADATA
grafci-0.1.0.dist-info/RECORD
