Metadata-Version: 2.1
Name: grafci
Version: 0.1.0
Summary: 
Home-page: https://github.com/nichmor/grafci
License: MIT
Author: nichitaelgraf
Requires-Python: >=3.10,<4.0
Classifier: License :: OSI Approved :: MIT License
Classifier: Programming Language :: Python :: 3
Classifier: Programming Language :: Python :: 3.10
Requires-Dist: autopep8 (>=1.6.0,<2.0.0)
Requires-Dist: isort (>=5.10.1,<6.0.0)
Requires-Dist: mkdocs (>=1.3.1,<2.0.0)
Requires-Dist: pytest (>=7.1.2,<8.0.0)
Requires-Dist: pytest-cov (>=3.0.0,<4.0.0)
Requires-Dist: unify (>=0.5,<0.6)
Requires-Dist: wemake-python-styleguide (>=0.16.1,<0.17.0)
Project-URL: Repository, https://github.com/nichmor/grafci
